cpf_utils/__init__.py
cpf_utils/cpf_utils.py
cpf_utils-1.0.1.dist-info/licenses/LICENSE
cpf_utils-1.0.1.dist-info/METADATA
cpf_utils-1.0.1.dist-info/WHEEL
cpf_utils-1.0.1.dist-info/top_level.txt
cpf_utils-1.0.1.dist-info/RECORD
