Metadata-Version: 2.4
Name: cpf-utils
Version: 1.0.1
Summary: Utility functions to deal with CPF data (Brazilian personal ID)
Author: Julio L. Muller
License-Expression: MIT
Project-URL: Homepage, https://cpf-utils.vercel.app/
Project-URL: Source, https://github.com/LacusSolutions/br-utils-py
Project-URL: Tracker, https://github.com/LacusSolutions/br-utils-py/issues
Keywords: cpf,validar,validador,validate,validation,formatar,format,gerar,gerador,generate,generator,pt-br,br
Classifier: Development Status :: 5 - Production/Stable
Classifier: Intended Audience :: Developers
Classifier: Natural Language :: English
Classifier: Natural Language :: Portuguese (Brazilian)
Classifier: Operating System :: MacOS :: MacOS X
Classifier: Operating System :: Microsoft :: Windows
Classifier: Operating System :: POSIX
Classifier: Operating System :: Unix
Classifier: Programming Language :: Python :: 3 :: Only
Classifier: Programming Language :: Python :: 3.10
Classifier: Programming Language :: Python :: 3.11
Classifier: Programming Language :: Python :: 3.12
Classifier: Programming Language :: Python :: 3.13
Classifier: Programming Language :: Python :: 3.14
Classifier: Topic :: Software Development :: Libraries
Classifier: Topic :: Utilities
Requires-Python: >=3.10
License-File: LICENSE
Requires-Dist: cpf-fmt<2.0.0,>=1.0.0
Requires-Dist: cpf-gen<2.0.0,>=1.0.1
Requires-Dist: cpf-val<2.0.0,>=1.0.1
Dynamic: license-file
